opsanalyze/__init__.py
opsanalyze/analyze.py
opsanalyze-2.2.dist-info/METADATA
opsanalyze-2.2.dist-info/WHEEL
opsanalyze-2.2.dist-info/licenses/LICENSE
opsanalyze-2.2.dist-info/RECORD
