Metadata-Version: 2.1
Name: opsanalyze
Version: 2.2
Summary: A python package for performing different kinds of analysis on openseespy models.
Author-email: Okhtai Alizadeh Arasi <ok.programss@gmail.com>
License-File: LICENSE
Classifier: License :: OSI Approved :: MIT License
Classifier: Operating System :: Microsoft :: Windows
Classifier: Programming Language :: Python :: 3
Requires-Python: >=3.9
